python_microscopy-25.6.5.dist-info/METADATA
python_microscopy-25.6.5.dist-info/WHEEL
PYME/Analysis/points/SoftRend/triRend.cpython-39-darwin.so
PYME/Analysis/points/DistHist/distHist.cpython-39-darwin.so
PYME/Analysis/points/DeClump/deClump.cpython-39-darwin.so
PYME/Analysis/points/EdgeDB/edgeDB.cpython-39-darwin.so
PYME/Analysis/points/arcfit/arcmf.cpython-39-darwin.so
PYME/Analysis/points/astigmatism/astiglookup.cpython-39-darwin.so
PYME/Analysis/points/traveling_salesperson/two_opt_utils.cpython-39-darwin.so
PYME/Analysis/PSFGen/ps_app.cpython-39-darwin.so
PYME/Acquire/Hardware/Simulator/illuminate.cpython-39-darwin.so
PYME/DSView/LUT/lut.cpython-39-darwin.so
PYME/IO/countdir/countdir.cpython-39-darwin.so
PYME/IO/buffer_helpers.cpython-39-darwin.so
PYME/localization/cModels/gauss_app.cpython-39-darwin.so
PYME/localization/cInterp/cInterp.cpython-39-darwin.so
PYME/contrib/gohlke/_tifffile.cpython-39-darwin.so
PYME/experimental/_triangle_mesh.cpython-39-darwin.so
PYME/experimental/_octree.cpython-39-darwin.so
PYME/experimental/_treap.cpython-39-darwin.so
PYME/experimental/func_octree.cpython-39-darwin.so
PYME/experimental/triangle_mesh_utils.cpython-39-darwin.so
PYME/update_version.py
PYME/config.py
PYME/version.py
PYME/setup_exe.py
PYME/__init__.py
PYME/setup.py
PYME/pyme_warnings.py
PYME/Analysis/piecewiseMapping.py
PYME/Analysis/distributed_pyramid.py
PYME/Analysis/tile_pyramid.py
PYME/Analysis/widefieldify.py
PYME/Analysis/graphing_filters.py
PYME/Analysis/MetaData.py
PYME/Analysis/splitting.py
PYME/Analysis/fiducial_matching.py
PYME/Analysis/implicitFilter.py
PYME/Analysis/density_filter.py
PYME/Analysis/processLogger.py
PYME/Analysis/optic_flow.py
PYME/Analysis/svmSegment.py
PYME/Analysis/angleFilter.py
PYME/Analysis/gen_sCMOS_maps.py
PYME/Analysis/__init__.py
PYME/Analysis/thresholding.py
PYME/Analysis/annealThresh.py
PYME/Analysis/_fithelpers.py
PYME/Analysis/profile_extraction.py
PYME/Analysis/setup.py
PYME/Analysis/cramerRao.py
PYME/Analysis/piezo_movement_correction.py
PYME/Analysis/composite.py
PYME/Analysis/deTile.py
python_microscopy-25.6.5.dist-info/RECORD
