Metadata-Version: 2.1
Name: python-microscopy
Version: 25.6.5
Summary: Tools for (super-resolution) microscopy data analysis and microsope control
Author-Email: David Baddeley <d.baddeley@auckland.ac.nz>
Classifier: Programming Language :: Python :: 3
Classifier: License :: OSI Approved :: GNU General Public License v3 (GPLv3)
Classifier: Operating System :: OS Independent
Project-URL: Homepage, https://github.com/python-microscopy/pymecompress
Requires-Python: >=3.8
Requires-Dist: numpy>=1.22
Requires-Dist: scipy
Requires-Dist: matplotlib
Requires-Dist: wxpython
Requires-Dist: cython
Requires-Dist: pytables
Requires-Dist: pyopengl
Requires-Dist: traits
Requires-Dist: traitsui>=7.6.0
Requires-Dist: pyface>=7.6.0
Requires-Dist: pillow
Requires-Dist: toposort
Requires-Dist: networkx
Requires-Dist: pyfftw
Requires-Dist: cherrypy
Requires-Dist: scikit-image
Requires-Dist: scikit-learn
Requires-Dist: zeroconf
Requires-Dist: requests
Requires-Dist: pandas
Requires-Dist: pyyaml
Requires-Dist: psutil
Requires-Dist: docutils
Requires-Dist: sphinx
Requires-Dist: ujson>=3.0.0
Requires-Dist: jinja2
Requires-Dist: pycairo
Requires-Dist: pymecompress>=0.2.0
Requires-Dist: six
Requires-Dist: future
Requires-Dist: blosc
Requires-Dist: django>=2.1
